Metadata-Version: 2.1
Name: odoo12-addon-purchase-triple-discount
Version: 12.0.1.1.0
Summary: Manage triple discount on purchase order lines
Home-page: https://github.com/OCA/purchase-workflow
Author: Tecnativa,GRAP,Odoo Community Association (OCA)
Author-email: support@odoo-community.org
License: AGPL-3
Platform: UNKNOWN
Classifier: Programming Language :: Python
Classifier: Framework :: Odoo
Classifier: License :: OSI Approved :: GNU Affero General Public License v3
Requires-Python: >=3.5
Requires-Dist: odoo12-addon-account-invoice-triple-discount
Requires-Dist: odoo12-addon-purchase-discount
Requires-Dist: odoo (<12.1dev,>=12.0a)
